{
    "ExportResult": "Export Ergebnis",
    "Warning": "Warnung:",
    "ExportErrorsOccured": "Es sind Fehler beim Export aufgetreten.",
    "ExportErrorsCountPrefix": "(",
    "ExportErrorsCountPostfix": "x)",
    "Download": "Herunterladen",
    "CopyToClipboard": "In die Zwischenablage kopieren",
    "SuccessfullyCopiedToClipboard": "Code wurde in die zwischenablage kopiert",

    "UnsavedChanges": "Ungespeicherte Änderungen",
    "AreYouSureYouWantToExportUnsavedChanges": "Es liegen ungespeicherte Änderungen vor. Der Export wird einen veralteten Stand reflektieren. Bist du sicher das du einen veralteten Stand exportieren willst?",

    "Ok": "Ok",
    "Yes": "Ja",
    "No": "Nein"
}